postalert/__init__.py
postalert/__main__.py
postalert/config.yml
postalert/leak_alerts.py
postalert-0.1.2.dist-info/METADATA
postalert-0.1.2.dist-info/WHEEL
postalert-0.1.2.dist-info/entry_points.txt
postalert-0.1.2.dist-info/top_level.txt
postalert-0.1.2.dist-info/RECORD
