Metadata-Version: 2.4
Name: postalert
Version: 0.1.2
Summary: PostAlert bug bounty secret scanning tool with Discord alerts
Author: Muthu D.
Author-email: talktomtuhud@gmail.com
Requires-Dist: requests
Requires-Dist: PyYAML
Requires-Dist: tldextract
Requires-Dist: whispers
Dynamic: author
Dynamic: author-email
Dynamic: requires-dist
Dynamic: summary
